PySeoHtml/__init__.py
PySeoHtml/lib.py
PySeoHtml/test.py
py_seo_html-1.2.1.dist-info/LICENSE
py_seo_html-1.2.1.dist-info/METADATA
py_seo_html-1.2.1.dist-info/WHEEL
py_seo_html-1.2.1.dist-info/top_level.txt
py_seo_html-1.2.1.dist-info/RECORD
